gym_saturation/__init__.py
gym_saturation/constants.py
gym_saturation/envs/__init__.py
gym_saturation/envs/iprover_env.py
gym_saturation/envs/saturation_env.py
gym_saturation/envs/vampire_env.py
gym_saturation/py.typed
gym_saturation/relay_server.py
gym_saturation/resources/TPTP-mock/Problems/TST/TST001-1.p
gym_saturation/resources/TPTP-mock/Problems/TST/TST002-1.p
gym_saturation/resources/vampire-mock
gym_saturation/vampire_wrapper.py
gym_saturation/wrappers/__init__.py
gym_saturation/wrappers/labels_extractor.py
gym_saturation-1.0.4.dist-info/METADATA
gym_saturation-1.0.4.dist-info/WHEEL
gym_saturation-1.0.4.dist-info/licenses/LICENSE
gym_saturation-1.0.4.dist-info/RECORD
