Metadata-Version: 2.4
Name: gym-saturation
Version: 1.0.4
Summary: Gymnasium environments for saturation provers
License-File: LICENSE
Keywords: saturation prover,OpenAI Gym,Gymnasium,automated theorem prover
Author: Boris Shminke
Author-email: <boris@shminke.com>
Requires-Python: >= 3.10.0, < 3.14
Classifier: Programming Language :: Python :: 3.10
Classifier: Programming Language :: Python :: 3.11
Classifier: Programming Language :: Python :: 3.12
Classifier: Programming Language :: Python :: 3.13
Classifier: License :: OSI Approved :: Apache Software License
Classifier: Operating System :: OS Independent
Classifier: Intended Audience :: Science/Research
Classifier: Development Status :: 7 - Inactive
Classifier: Environment :: Console
Classifier: Natural Language :: English
Classifier: Topic :: Scientific/Engineering :: Artificial Intelligence
Classifier: Typing :: Typed
Provides-Extra: dev
Provides-Extra: doc
Provides-Extra: test
Requires-Dist: coverage ; extra == "test"
Requires-Dist: debugpy ; extra == "dev"
Requires-Dist: furo ; extra == "doc"
Requires-Dist: gymnasium
Requires-Dist: isort ; extra == "dev"
Requires-Dist: jedi-language-server ; extra == "dev"
Requires-Dist: pexpect
Requires-Dist: pre-commit ; extra == "dev"
Requires-Dist: pydoclint ; extra == "dev"
Requires-Dist: pyrefly ; extra == "dev"
Requires-Dist: pyrefly ; extra == "dev"
Requires-Dist: pyroma ; extra == "dev"
Requires-Dist: pytest ; extra == "test"
Requires-Dist: ruff ; extra == "dev"
Requires-Dist: sphinx-autodoc-typehints ; extra == "doc"
Requires-Dist: tbump ; extra == "dev"
Requires-Dist: toml ; extra == "dev"
Requires-Dist: types-dataclasses ; extra == "doc"
Project-URL: Documentation, https://gym-saturation.readthedocs.io
Project-URL: Issues, https://github.com/inpefess/gym-saturation/issues
Project-URL: Repository, https://github.com/inpefess/gym-saturation.git
